chunked_scatter/__init__.py
chunked_scatter/chunked_scatter.py
chunked_scatter/parsers.py
chunked_scatter/scatter_regions.py
chunked_scatter-1.0.0.dist-info/LICENSE
chunked_scatter-1.0.0.dist-info/METADATA
chunked_scatter-1.0.0.dist-info/WHEEL
chunked_scatter-1.0.0.dist-info/entry_points.txt
chunked_scatter-1.0.0.dist-info/top_level.txt
chunked_scatter-1.0.0.dist-info/RECORD
