Metadata-Version: 2.1
Name: chunked-scatter
Version: 1.0.0
Summary: Chunk and scatter the regions in a bed or sequence dict file
Home-page: https://github.com/biowdl/chunked-scatter
Author: Leiden University Medical Center
Author-email: sasc@lumc.nl
License: MIT
Keywords: bioinformatics
Platform: UNKNOWN
Classifier: Programming Language :: Python :: 3 :: Only
Classifier: Programming Language :: Python :: 3
Classifier: Programming Language :: Python :: 3.6
Classifier: Programming Language :: Python :: 3.7
Classifier: Programming Language :: Python :: 3.8
Classifier: Topic :: Scientific/Engineering :: Bio-Informatics
Classifier: Development Status :: 3 - Alpha
Classifier: License :: OSI Approved :: MIT License
Requires-Python: >=3.6
Requires-Dist: pysam (>=0.11.2)
